{
    "taskDefinitionArn": "arn:aws:ecs:eu-west-1:629517020360:task-definition/vacationer-task-definition:12",
    "containerDefinitions": [
        {
            "name": "vacationer-app",
            "image": "629517020360.dkr.ecr.eu-west-1.amazonaws.com/ecr-vacationer:404fba7f462f32ec480736d8577e2696086e336e",
            "cpu": 0,
            "links": [],
            "portMappings": [
                {
                    "containerPort": 3000,
                    "hostPort": 3000,
                    "protocol": "tcp"
                }
            ],
            "essential": true,
            "entryPoint": [],
            "command": [],
            "environment": [],
            "mountPoints": [],
            "volumesFrom": [],
            "logConfiguration": {
                "logDriver": "awslogs",
                "options": {
                    "awslogs-group": "/ecs/vacationer-task-definition",
                    "awslogs-region": "eu-west-1",
                    "awslogs-stream-prefix": "ecs"
                }
            }
        }
    ],
    "family": "vacationer-task-definition",
    "executionRoleArn": "arn:aws:iam::629517020360:role/ecsTaskExecutionRole",
    "networkMode": "awsvpc",
    "revision": 12,
    "volumes": [],
    "status": "ACTIVE",
    "requiresAttributes": [
        {
            "name": "com.amazonaws.ecs.capability.logging-driver.awslogs"
        },
        {
            "name": "ecs.capability.execution-role-awslogs"
        },
        {
            "name": "com.amazonaws.ecs.capability.ecr-auth"
        },
        {
            "name": "com.amazonaws.ecs.capability.docker-remote-api.1.19"
        },
        {
            "name": "ecs.capability.execution-role-ecr-pull"
        },
        {
            "name": "com.amazonaws.ecs.capability.docker-remote-api.1.18"
        },
        {
            "name": "ecs.capability.task-eni"
        }
    ],
    "placementConstraints": [],
    "compatibilities": [
        "EC2",
        "FARGATE"
    ],
    "requiresCompatibilities": [
        "FARGATE"
    ],
    "cpu": "256",
    "memory": "512",
    "registeredAt": "2022-08-09T09:40:59.660000+03:00",
    "registeredBy": "arn:aws:sts::629517020360:assumed-role/TietoCemAmsSandbox/kimmo.perala@tietoevry.com"
}
